AUTHORS.rst
CONTRIBUTING.rst
HISTORY.rst
LICENSE
MANIFEST.in
README.rst
setup.cfg
setup.py
docs/Makefile
docs/authors.rst
docs/conf.py
docs/contributing.rst
docs/history.rst
docs/index.rst
docs/installation.rst
docs/make.bat
docs/readme.rst
docs/usage.rst
tests/__init__.py
tests/test_tv_db_api.py
tv_db_api/__init__.py
tv_db_api/default_field_config.py
tv_db_api/tv_db_api.py
tv_db_api.egg-info/PKG-INFO
tv_db_api.egg-info/SOURCES.txt
tv_db_api.egg-info/dependency_links.txt
tv_db_api.egg-info/not-zip-safe
tv_db_api.egg-info/requires.txt
tv_db_api.egg-info/top_level.txt