Metadata-Version: 2.1
Name: tv-db-api
Version: 0.1.3
Summary: Python wrapper for interacting with the tv db api
Home-page: https://github.com/paul-armstrong-dev/tv_db_api
Author: Paul Armstrong
Author-email: paul.armstrong211@gmail.com
License: MIT license
Keywords: tv_db_api
Classifier: Development Status :: 2 - Pre-Alpha
Classifier: Intended Audience :: Developers
Classifier: License :: OSI Approved :: MIT License
Classifier: Natural Language :: English
Classifier: Programming Language :: Python :: 3
Classifier: Programming Language :: Python :: 3.6
Classifier: Programming Language :: Python :: 3.7
Classifier: Programming Language :: Python :: 3.8
Requires-Python: >=3.6
License-File: LICENSE
License-File: AUTHORS.rst
